urlquick.py
urlquick-2.0.1.dist-info/LICENSE
urlquick-2.0.1.dist-info/METADATA
urlquick-2.0.1.dist-info/WHEEL
urlquick-2.0.1.dist-info/top_level.txt
urlquick-2.0.1.dist-info/RECORD
