Metadata-Version: 2.1
Name: urlquick
Version: 2.0.1
Summary: Requests wrapper that add's support for HTTP caching. It act's just like requests but with a few extra parameters and features.
Home-page: https://github.com/willforde/urlquick
Author: William Forde
Author-email: willforde@gmail.com
License: MIT
Project-URL: Documentation, http://urlquick.readthedocs.io/en/stable/?badge=stable
Project-URL: Source, https://github.com/willforde/urlquick
Keywords: python,http,caching,requests
Platform: UNKNOWN
Classifier: Development Status :: 5 - Production/Stable
Classifier: Intended Audience :: Developers
Classifier: Natural Language :: English
Classifier: License :: OSI Approved :: MIT License
Classifier: Topic :: Internet :: WWW/HTTP
Classifier: Topic :: Software Development :: Libraries :: Python Modules
Classifier: Programming Language :: Python :: 2
Classifier: Programming Language :: Python :: 2.7
Classifier: Programming Language :: Python :: 3
Classifier: Programming Language :: Python :: 3.6
Classifier: Programming Language :: Python :: 3.7
Classifier: Programming Language :: Python :: 3.8
Classifier: Programming Language :: Python :: 3.9
Requires-Python: !=3.0.*,!=3.1.*,!=3.2.*,!=3.3.*,!=3.4.*,!=3.5.*,>=2.7
Requires-Dist: requests
Requires-Dist: htmlement
Provides-Extra: dev
Requires-Dist: tox ; extra == 'dev'
Requires-Dist: pytest ; extra == 'dev'
Requires-Dist: pytest-cov ; extra == 'dev'
Requires-Dist: pytest-mock ; extra == 'dev'
